showdown/__init__.py
showdown/client.py
showdown/docutils.py
showdown/message.py
showdown/room.py
showdown/server.py
showdown/user.py
showdown/utils.py
showdownpy-0.1.5.dist-info/LICENSE
showdownpy-0.1.5.dist-info/METADATA
showdownpy-0.1.5.dist-info/WHEEL
showdownpy-0.1.5.dist-info/top_level.txt
showdownpy-0.1.5.dist-info/RECORD
