Metadata-Version: 2.1
Name: showdownpy
Version: 0.1.5
Summary: An extendable client for interacting with Pokemon Showdown
Home-page: https://github.com/ckw017/showdown.py
Author: Chris K. W.
Author-email: chriskw.xyz@gmail.com
License: MIT
Platform: UNKNOWN
Classifier: Development Status :: 4 - Beta
Classifier: License :: OSI Approved :: MIT License
Classifier: Intended Audience :: Developers
Classifier: Programming Language :: Python :: 3.5
Classifier: Operating System :: OS Independent
Classifier: Natural Language :: English
Classifier: Topic :: Internet
Classifier: Topic :: Utilities
Classifier: Topic :: Games/Entertainment :: Turn Based Strategy
Classifier: Topic :: Communications :: Chat
Requires-Dist: websockets
Requires-Dist: aiohttp
